cex/__init__.py
cex/cex_name.py
cex/symbol.py
cex/bnc/__init__.py
cex/bnc/endpoints.py
cex/bnc/enums.py
cex/bnc/public.py
cex/bnc/public_cm.py
cex/bnc/public_spot.py
cex/bnc/public_um.py
cex/bnc/rest.py
cex/bnc/sign.py
cex/bnc/user.py
cex/ob/__init__.py
cex/ob/ob.py
pycex-0.0.5.dist-info/METADATA
pycex-0.0.5.dist-info/WHEEL
pycex-0.0.5.dist-info/top_level.txt
pycex-0.0.5.dist-info/RECORD
