Metadata-Version: 2.4
Name: pycex
Version: 0.0.5
Home-page: https://github.com/dwdwow/pycex
Requires-Dist: requests
Requires-Dist: urllib3
Dynamic: description
Dynamic: description-content-type
Dynamic: home-page
Dynamic: requires-dist
